PyNUTClient/PyNUT.py
PyNUTClient/__init__.py
PyNUTClient/test_nutclient.py
pynutclient-2.8.4.dist-info/licenses/LICENSE-GPL3
pynutclient-2.8.4.dist-info/METADATA
pynutclient-2.8.4.dist-info/WHEEL
pynutclient-2.8.4.dist-info/top_level.txt
pynutclient-2.8.4.dist-info/RECORD
