Metadata-Version: 2.4
Name: pynutclient
Version: 2.8.4
Summary: Python client bindings for NUT
Home-page: https://github.com/networkupstools/nut/tree/master/scripts/python/module
Author: The Network UPS Tools project
Author-email: jimklimov+nut@gmail.com
License: GPL-3.0-or-later
Keywords: pypi,cicd,python,nut,Network UPS Tools
Classifier: Development Status :: 5 - Production/Stable
Classifier: Intended Audience :: Developers
Classifier: Intended Audience :: System Administrators
Classifier: Topic :: System :: Monitoring
Classifier: Topic :: System :: Systems Administration
Classifier: License :: OSI Approved :: GNU General Public License v3 or later (GPLv3+)
Classifier: Programming Language :: Python :: 2.6
Classifier: Programming Language :: Python :: 2.7
Classifier: Programming Language :: Python :: 3
Classifier: Operating System :: Unix
Classifier: Operating System :: MacOS :: MacOS X
Classifier: Operating System :: Microsoft :: Windows
Requires-Python: >=2.6
License-File: LICENSE-GPL3
Dynamic: author
Dynamic: author-email
Dynamic: classifier
Dynamic: description
Dynamic: description-content-type
Dynamic: home-page
Dynamic: keywords
Dynamic: license
Dynamic: license-file
Dynamic: requires-python
Dynamic: summary
